AutoBuffssssss/__init__.py
AutoBuffssssss/__main__.py
AutoBuffssssss/pytransform/__init__.py
AutoBuffssssss/pytransform/_pytransform.dll
autobuffssssss-0.1.19.dist-info/METADATA
autobuffssssss-0.1.19.dist-info/WHEEL
autobuffssssss-0.1.19.dist-info/RECORD
