Metadata-Version: 2.1
Name: autobuffssssss
Version: 0.1.19
Summary: 
Author: SDK
Requires-Python: >=3.10,<4.0
Classifier: Programming Language :: Python :: 3
Classifier: Programming Language :: Python :: 3.10
Classifier: Programming Language :: Python :: 3.11
Requires-Dist: customtkinter (>=5.1.2,<6.0.0)
Requires-Dist: easyimap (>=0.7.0,<0.8.0)
Requires-Dist: opencv-python (>=4.7.0.72,<5.0.0.0)
Requires-Dist: pillow (>=9.4.0,<10.0.0)
Requires-Dist: pyautogui (>=0.9.53,<0.10.0)
Requires-Dist: pygetwindow (>=0.0.9,<0.0.10)
Requires-Dist: requests (>=2.28.2,<3.0.0)
